pynputfix/__init__.py
pynputfix/_info.py
pynputfix/_util/__init__.py
pynputfix/_util/darwin.py
pynputfix/_util/darwin_vks.py
pynputfix/_util/uinput.py
pynputfix/_util/win32.py
pynputfix/_util/win32_vks.py
pynputfix/_util/xorg.py
pynputfix/_util/xorg_keysyms.py
pynputfix/keyboard/__init__.py
pynputfix/keyboard/_base.py
pynputfix/keyboard/_darwin.py
pynputfix/keyboard/_dummy.py
pynputfix/keyboard/_uinput.py
pynputfix/keyboard/_win32.py
pynputfix/keyboard/_xorg.py
pynputfix/mouse/__init__.py
pynputfix/mouse/_base.py
pynputfix/mouse/_darwin.py
pynputfix/mouse/_dummy.py
pynputfix/mouse/_win32.py
pynputfix/mouse/_xorg.py
pynputfix-1.8.2.dist-info/licenses/COPYING.LGPL
pynputfix-1.8.2.dist-info/METADATA
pynputfix-1.8.2.dist-info/WHEEL
pynputfix-1.8.2.dist-info/top_level.txt
pynputfix-1.8.2.dist-info/zip-safe
pynputfix-1.8.2.dist-info/RECORD
