Metadata-Version: 2.4
Name: pynputfix
Version: 1.8.2
Summary: Monitor and control user input devices
Home-page: https://github.com/AuroraWright/pynputfix
Author: Moses Palmér
Author-email: fallingluma@gmail.com
License: LGPLv3
Keywords: control mouse,mouse input,control keyboard,keyboard input
Classifier: Development Status :: 5 - Production/Stable
Classifier: Intended Audience :: Developers
Classifier: License :: OSI Approved :: GNU Lesser General Public License v3 (LGPLv3)
Classifier: Operating System :: MacOS :: MacOS X
Classifier: Operating System :: Microsoft :: Windows :: Windows NT/2000
Classifier: Operating System :: POSIX
Classifier: Programming Language :: Python
Classifier: Programming Language :: Python :: 2.7
Classifier: Programming Language :: Python :: 3.4
Classifier: Programming Language :: Python :: 3.5
Classifier: Programming Language :: Python :: 3.6
Classifier: Programming Language :: Python :: 3.7
Classifier: Programming Language :: Python :: 3.8
Classifier: Programming Language :: Python :: 3.9
Classifier: Topic :: Software Development :: Libraries :: Python Modules
Classifier: Topic :: System :: Monitoring
License-File: COPYING.LGPL
Requires-Dist: six
Requires-Dist: pyobjc-framework-ApplicationServices>=8.0; sys_platform == "darwin"
Requires-Dist: pyobjc-framework-Quartz>=8.0; sys_platform == "darwin"
Requires-Dist: evdev>=1.3; "linux" in sys_platform
Requires-Dist: python-xlib>=0.17; "linux" in sys_platform
Requires-Dist: enum34; python_version == "2.7"
Dynamic: author
Dynamic: author-email
Dynamic: classifier
Dynamic: description
Dynamic: home-page
Dynamic: keywords
Dynamic: license
Dynamic: license-file
Dynamic: provides-extra
Dynamic: requires-dist
Dynamic: summary
